skill_hub/__init__.py
skill_hub/__main__.py
skill_hub/commands/__init__.py
skill_hub/commands/install.py
skill_hub/commands/list.py
skill_hub/commands/manage.py
skill_hub/commands/mng.py
skill_hub/commands/repo.py
skill_hub/commands/search.py
skill_hub/commands/sync.py
skill_hub/commands/uninstall.py
skill_hub/commands/update.py
skill_hub/utils/__init__.py
skill_hub/utils/agent_cmd.py
skill_hub/utils/display.py
skill_hub/utils/skill_mng.py
agent_skills_hub-1.6.10.dist-info/LICENSE
agent_skills_hub-1.6.10.dist-info/METADATA
agent_skills_hub-1.6.10.dist-info/WHEEL
agent_skills_hub-1.6.10.dist-info/entry_points.txt
agent_skills_hub-1.6.10.dist-info/top_level.txt
agent_skills_hub-1.6.10.dist-info/RECORD
