Metadata-Version: 2.1
Name: agent-skills-hub
Version: 1.6.10
Summary: A package manager for Agent skills
Author: youzaiAGI
Author-email: youzaiagi@gmail.com
Classifier: Development Status :: 3 - Alpha
Classifier: Intended Audience :: Developers
Classifier: License :: OSI Approved :: MIT License
Classifier: Operating System :: OS Independent
Classifier: Programming Language :: Python :: 3
Classifier: Programming Language :: Python :: 3.7
Classifier: Programming Language :: Python :: 3.8
Classifier: Programming Language :: Python :: 3.9
Classifier: Programming Language :: Python :: 3.10
Requires-Python: >=3.7
License-File: LICENSE
Requires-Dist: requests (>=2.25.1)
Requires-Dist: windows-curses (>=2.3.0) ; sys_platform == "win32"
